image_processing_ottojacometo/__init__.py
image_processing_ottojacometo/processing/__init__.py
image_processing_ottojacometo/processing/combination.py
image_processing_ottojacometo/processing/transformation.py
image_processing_ottojacometo/utils/__init__.py
image_processing_ottojacometo/utils/io.py
image_processing_ottojacometo/utils/plot.py
image_processing_ottojacometo-0.0.1.dist-info/METADATA
image_processing_ottojacometo-0.0.1.dist-info/WHEEL
image_processing_ottojacometo-0.0.1.dist-info/top_level.txt
image_processing_ottojacometo-0.0.1.dist-info/RECORD
