Metadata-Version: 2.1
Name: image_processing_ottojacometo
Version: 0.0.1
Summary: Realiza o processamento de imagens (combinação e transformação).
Home-page: https://github.com/Otto-21/image_processing_package.git
Author: Otto-21
Author-email: otto.jacometo@gmail.com
Requires-Python: >=3.8
